{
  "annotations": {
    "list": [
      {
        "builtIn": 1,
        "datasource": {
          "type": "grafana",
          "uid": "-- Grafana --"
        },
        "enable": true,
        "hide": true,
        "iconColor": "rgba(0, 211, 255, 1)",
        "name": "Annotations & Alerts",
        "type": "dashboard"
      }
    ]
  },
  "editable": true,
  "graphTooltip": 0,
  "panels": [
    {
      "datasource": {
        "type": "cloudwatch",
        "uid": "CLOUDWATCH"
      },
      "gridPos": {
        "x": 0,
        "y": 8,
        "w": 24,
        "h": 10
      },
      "id": 7,
      "targets": [
        {
          "datasource": {
            "type": "cloudwatch",
            "uid": "CLOUDWATCH"
          },
          "logGroups": [
            {
              "accountId": "GRAFANA_CLOUDWATCH_ACCOUNT_ID",
              "arn": "arn:aws:logs:eu-west-2:GRAFANA_CLOUDWATCH_ACCOUNT_ID:log-group:$waf_log_group:*",
              "name": "$waf_log_group"
            }
          ],
          "queryMode": "Logs",
          "refId": "A",
          "region": "default",
          "sqlExpression": "",
          "expression": "fields @timestamp\n| parse @message /\"webaclId\":\"(?<webaclId>[^\"]+)\"/\n| parse @message /\"clientIp\":\"(?<ip>[^\"]+)\"/\n| parse @message /\"country\":\"(?<country>[^\"]+)\"/\n| parse @message /\"uri\":\"(?<uri>[^\"]+)\"/\n| parse @message /\"httpMethod\":\"(?<method>[^\"]+)\"/\n| parse @message /\"action\":\"(?<action>[^\"]+)\"/\n| parse @message /\"terminatingRuleId\":\"(?<terminatingRuleId>[^\"]+)\"/\n| filter webaclId like /$web_acl/\n| filter action like /$action_filter/\n| filter uri like /$uri_filter/\n| sort @timestamp desc\n| limit 200",
          "queryLanguage": "CWLI",
          "metricName": "",
          "statistic": "Average"
        }
      ],
      "title": "Recent Requests (WAF)",
      "type": "table",
      "transformations": [
        {
          "id": "organize",
          "options": {
            "excludeByName": {
              "Value": true,
              "@message": true
            },
            "indexByName": {
              "@timestamp": 0,
              "ip": 1,
              "country": 2,
              "method": 3,
              "uri": 4,
              "action": 5,
              "terminatingRuleId": 6
            }
          }
        }
      ]
    },
    {
      "datasource": {
        "type": "cloudwatch",
        "uid": "CLOUDWATCH"
      },
      "gridPos": {
        "x": 0,
        "y": 0,
        "w": 12,
        "h": 8
      },
      "id": 8,
      "title": "Top Client IPs (last 15m)",
      "type": "table",
      "targets": [
        {
          "datasource": {
            "type": "cloudwatch",
            "uid": "CLOUDWATCH"
          },
          "queryMode": "Logs",
          "queryLanguage": "CWLI",
          "refId": "A",
          "expression": "fields @timestamp\n| parse @message /\"webaclId\":\"(?<webaclId>[^\"]+)\"/\n| parse @message /\"clientIp\":\"(?<ip>[^\"]+)\"/\n| parse @message /\"action\":\"(?<action>[^\"]+)\"/\n| filter webaclId like /$web_acl/\n| filter action like /$action_filter/\n| filter @timestamp >= ago(15m)\n| stats count() as requests by ip\n| sort requests desc",
          "logGroups": [
            {
              "accountId": "GRAFANA_CLOUDWATCH_ACCOUNT_ID",
              "arn": "arn:aws:logs:eu-west-2:GRAFANA_CLOUDWATCH_ACCOUNT_ID:log-group:$waf_log_group:*",
              "name": "$waf_log_group"
            }
          ],
          "region": "default",
          "statistic": "Average",
          "metricName": "",
          "namespace": "",
          "metricQueryType": 0,
          "sqlExpression": ""
        }
      ],
      "transformations": [
        {
          "id": "organize",
          "options": {
            "excludeByName": {
              "Value": true,
              "@message": true,
              "Time": true
            },
            "indexByName": {
              "ip": 0,
              "requests": 1
            }
          }
        }
      ]
    },
    {
      "datasource": {
        "type": "cloudwatch",
        "uid": "CLOUDWATCH"
      },
      "gridPos": {
        "x": 12,
        "y": 0,
        "w": 12,
        "h": 8
      },
      "id": 9,
      "title": "Top URIs (filtered)",
      "type": "table",
      "targets": [
        {
          "datasource": {
            "type": "cloudwatch",
            "uid": "CLOUDWATCH"
          },
          "queryMode": "Logs",
          "queryLanguage": "CWLI",
          "refId": "A",
          "expression": "fields @timestamp\n| parse @message /\"webaclId\":\"(?<webaclId>[^\"]+)\"/\n| parse @message /\"uri\":\"(?<uri>[^\"]+)\"/\n| parse @message /\"action\":\"(?<action>[^\"]+)\"/\n| filter webaclId like /$web_acl/\n| filter action like /$action_filter/\n| filter uri like /$uri_filter/\n| stats count() as requests by uri\n| sort requests desc",
          "logGroups": [
            {
              "accountId": "GRAFANA_CLOUDWATCH_ACCOUNT_ID",
              "arn": "arn:aws:logs:eu-west-2:GRAFANA_CLOUDWATCH_ACCOUNT_ID:log-group:$waf_log_group:*",
              "name": "$waf_log_group"
            }
          ],
          "region": "default",
          "statistic": "Average",
          "metricName": "",
          "namespace": "",
          "metricQueryType": 0,
          "sqlExpression": ""
        }
      ],
      "transformations": [
        {
          "id": "organize",
          "options": {
            "excludeByName": {
              "Value": true,
              "@message": true,
              "Time": true
            },
            "indexByName": {
              "uri": 0,
              "requests": 1
            }
          }
        }
      ]
    }
  ],
  "refresh": "30s",
  "schemaVersion": 39,
  "style": "dark",
  "tags": [
    "external",
    "traffic",
    "waf",
    "investigation"
  ],
  "templating": {
    "list": [
      {
        "name": "action_filter",
        "label": "WAF Action",
        "type": "custom",
        "includeAll": true,
        "allValue": ".*",
        "query": "ALLOW,BLOCK,COUNT",
        "options": [
          {
            "selected": false,
            "text": "ALLOW",
            "value": "ALLOW"
          },
          {
            "selected": false,
            "text": "BLOCK",
            "value": "BLOCK"
          },
          {
            "selected": false,
            "text": "COUNT",
            "value": "COUNT"
          }
        ],
        "current": {
          "text": [
            "$__all"
          ],
          "value": [
            "$__all"
          ]
        }
      },
      {
        "name": "web_acl",
        "label": "Web ACL",
        "type": "custom",
        "includeAll": true,
        "multi": true,
        "allValue": ".*",
        "query": "cdp-sirsi-acl,cdp-sirsi-php-acl,cdp-sirsi-fts-acl,cdp-sirsi-tools-acl",
        "options": [
          {
            "selected": false,
            "text": "cdp-sirsi-acl",
            "value": "cdp-sirsi-acl"
          },
          {
            "selected": false,
            "text": "cdp-sirsi-php-acl",
            "value": "cdp-sirsi-php-acl"
          },
          {
            "selected": false,
            "text": "cdp-sirsi-fts-acl",
            "value": "cdp-sirsi-fts-acl"
          },
          {
            "selected": false,
            "text": "cdp-sirsi-tools-acl",
            "value": "cdp-sirsi-tools-acl"
          }
        ],
        "current": {
          "text": [
            "All"
          ],
          "value": [
            "$__all"
          ]
        }
      },
      {
        "name": "waf_log_group",
        "label": "WAF Log Group",
        "type": "custom",
        "query": "aws-waf-logs-cdp-sirsi,aws-waf-logs-cdp-sirsi-php,aws-waf-logs-cdp-sirsi-fts,aws-waf-logs-cdp-sirsi-tools",
        "options": [
          {
            "selected": false,
            "text": "aws-waf-logs-cdp-sirsi",
            "value": "aws-waf-logs-cdp-sirsi"
          },
          {
            "selected": false,
            "text": "aws-waf-logs-cdp-sirsi-php",
            "value": "aws-waf-logs-cdp-sirsi-php"
          },
          {
            "selected": false,
            "text": "aws-waf-logs-cdp-sirsi-fts",
            "value": "aws-waf-logs-cdp-sirsi-fts"
          },
          {
            "selected": false,
            "text": "aws-waf-logs-cdp-sirsi-tools",
            "value": "aws-waf-logs-cdp-sirsi-tools"
          }
        ],
        "current": {
          "text": "aws-waf-logs-cdp-sirsi",
          "value": "aws-waf-logs-cdp-sirsi"
        }
      }
    ]
  },
  "time": {
    "from": "now-24h",
    "to": "now"
  },
  "timepicker": {
    "refresh_intervals": [
      "30s",
      "1m",
      "5m",
      "15m",
      "30m",
      "1h"
    ]
  },
  "timezone": "",
  "title": "External Traffic - WAF Investigations",
  "uid": "external-traffic-waf-investigations",
  "version": 1
}